nacis/__init__.py
nacis/features.py
nacis/preloader.py
nacispreloader-0.2.4.dist-info/METADATA
nacispreloader-0.2.4.dist-info/WHEEL
nacispreloader-0.2.4.dist-info/top_level.txt
nacispreloader-0.2.4.dist-info/RECORD
