Metadata-Version: 2.1
Name: nacispreloader
Version: 0.2.4
Summary: Preloader of nacis natural earth shapefiles
Home-page: UNKNOWN
Author: Steven Beale
Author-email: steven.beale@woodplc.com
License: MIT
Project-URL: Repo, https://bitbucket.org/amecfwmetocean/nacis/
Platform: UNKNOWN
Requires-Dist: cartopy
Requires-Dist: requests (>=2.26.0)
Requires-Dist: boto3 (>=1.18.47)
